{
  "WorkItem": {
    "AffectedComponent": {
      "Name": "",
      "DisplayName": ""
    },
    "ClosedComment": "",
    "ClosedDate": null,
    "CommentCount": 0,
    "Custom": null,
    "Description": "Hi\r\n\r\nis it plannes to get some Async CTP support?\r\n\r\nIt wold be great to have methods like SendMessageAsync which Return a Task. \r\nMostly interesseting for asynchronous processing of the messages and the flows they trigger",
    "LastUpdatedDate": "2017-12-08T09:36:31.49-08:00",
    "PlannedForRelease": "Triage",
    "ReleaseVisibleToPublic": true,
    "Priority": {
      "Name": "Low",
      "Severity": 50,
      "Id": 1
    },
    "ProjectName": "mvvmlight",
    "ReportedDate": "2011-11-05T06:37:37.123-07:00",
    "Status": {
      "Name": "Active",
      "Id": 2
    },
    "ReasonClosed": {
      "Name": "Unassigned"
    },
    "Summary": "Async CTP Support",
    "Type": {
      "Name": "Issue",
      "Id": 3
    },
    "VoteCount": 4,
    "Id": 7555
  },
  "FileAttachments": [],
  "Comments": []
}